pytorch_tabnet/__init__.py
pytorch_tabnet/abstract_model.py
pytorch_tabnet/augmentations.py
pytorch_tabnet/callbacks.py
pytorch_tabnet/data_handlers.py
pytorch_tabnet/metrics.py
pytorch_tabnet/multiclass_utils.py
pytorch_tabnet/multitask.py
pytorch_tabnet/pretraining.py
pytorch_tabnet/sparsemax.py
pytorch_tabnet/tab_model.py
pytorch_tabnet/tab_network.py
pytorch_tabnet/utils.py
eh_pytorch_tabnet-4.4.0.dist-info/METADATA
eh_pytorch_tabnet-4.4.0.dist-info/WHEEL
eh_pytorch_tabnet-4.4.0.dist-info/licenses/LICENSE
eh_pytorch_tabnet-4.4.0.dist-info/RECORD
