Metadata-Version: 2.4
Name: eh-pytorch-tabnet
Version: 4.4.0
Summary: PyTorch implementation of TabNet
License-File: LICENSE
Keywords: neural-networks,pytorch,tabnet
Requires-Python: >=3.10
Requires-Dist: numpy
Requires-Dist: scikit-learn
Requires-Dist: scipy
Requires-Dist: torch
Requires-Dist: torcheval
Requires-Dist: tqdm
